distributions_cyf
